adder/__init__.py
adder/main.py
multer/__init__.py
multer/main.py
calcor-1.0.dist-info/METADATA
calcor-1.0.dist-info/WHEEL
calcor-1.0.dist-info/top_level.txt
calcor-1.0.dist-info/RECORD
