Metadata-Version: 2.4
Name: calcor
Version: 1.0
Summary: simple example for packages
Author: Gneto dominique
Classifier: Programming Language :: Python :: 3
Dynamic: author
Dynamic: classifier
Dynamic: summary
